README.rst
setup.py
pyfarm/__init__.py
pyfarm.core.egg-info/PKG-INFO
pyfarm.core.egg-info/SOURCES.txt
pyfarm.core.egg-info/dependency_links.txt
pyfarm.core.egg-info/namespace_packages.txt
pyfarm.core.egg-info/requires.txt
pyfarm.core.egg-info/top_level.txt
pyfarm/core/__init__.py
pyfarm/core/config.py
pyfarm/core/enums.py
pyfarm/core/logger.py
pyfarm/core/testutil.py
pyfarm/core/utility.py