Metadata-Version: 1.1
Name: pyfarm.core
Version: 0.9.0
Summary: Sub-library which contains core modules, classes, and data types which are used by other parts of PyFarm.
Home-page: https://github.com/pyfarm/pyfarm-core
Author: Oliver Palmer
Author-email: development@pyfarm.net
License: Apache v2.0
Platform: UNKNOWN
Classifier: Development Status :: 4 - Beta
Classifier: Intended Audience :: Developers
Classifier: License :: OSI Approved :: Apache Software License
Classifier: Natural Language :: English
Classifier: Operating System :: OS Independent
Classifier: Programming Language :: Python :: 2
Classifier: Programming Language :: Python :: 3
Classifier: Topic :: System :: Distributed Computing
